echostream_function_context/__init__.py
echostream_function_context-0.1.0.dist-info/LICENSE
echostream_function_context-0.1.0.dist-info/METADATA
echostream_function_context-0.1.0.dist-info/WHEEL
echostream_function_context-0.1.0.dist-info/top_level.txt
echostream_function_context-0.1.0.dist-info/RECORD
