Metadata-Version: 2.1
Name: echostream-function-context
Version: 0.1.0
Summary: Micro library for typing function contexts in EchoStream functions
Author: EchoStream
Author-email: pypi@echo.stream
Requires-Python: >=3.12
License-File: LICENSE
Provides-Extra: dev
Requires-Dist: boto3-stubs[dynamodb] ; extra == 'dev'
